tglog/__init__.py
tglog/tglog.py
tglog-1.0.1.dist-info/LICENSE
tglog-1.0.1.dist-info/METADATA
tglog-1.0.1.dist-info/WHEEL
tglog-1.0.1.dist-info/top_level.txt
tglog-1.0.1.dist-info/RECORD
