Metadata-Version: 2.1
Name: tglog
Version: 1.0.1
Summary: Log errors in a log.txt file and receive them by telegram.
Home-page: https://github.com/cypg09/tglog
Author: cypg09
Author-email: cypg09@protonmail.com
License: UNKNOWN
Platform: UNKNOWN
Classifier: Programming Language :: Python :: 3
Classifier: License :: OSI Approved :: MIT License
Classifier: Operating System :: OS Independent
Requires-Python: >=3.6
